Workbook

Sheet Summary
A1: Subject: | B1: All-season and all-weather tires for a 2022 VW Taos Highline 4MOTION (Canada) — 225/50R18 95H standard, 225/45R19 92H optional 19" package
A2: Prepared: | B2: Sep 25 2026
A3: Skill: | B3: verified-comparison
A4: Currency: | B4: CAD $ · n/a (all prices are Canadian retailer list prices; no FX conversion)
A5: Tax: | B5: HST/GST/QST excluded
A6: Verification: | B6: [V] = read from the vendor's own source on the prepared date · [T] = third-party only · [U] = unverified
A8: Bottom line
A9: Answer | B9: Check your door-jamb placard first: 18" (225/50R18) is standard, 19" (225/45R19) is the $500 option. Cheapest all-weather: Pirelli Cinturato WeatherActive 18" at CAD $245.97/tire (Blackcircles) or Nitto Motivo 365 19" at CAD $273.70/tire (Blackcircles); benchmark Michelin CrossClimate 2 18" is CAD $321.95/tire at three retailers. [V]
A10: Price columns | B10: Retailer columns on the size sheets are CAD $ per tire, before tax, before mail-in rebates and promo codes. Installation is included only at Point S and Costco.
A12: Lowest per tire, by size and category
A13: Size / category | B13: Lowest CAD $ per tire | C13: Set of 4 (CAD $) | D13: Tire — retailer
A14: 225/50R18 · All-weather 3PMSF | B14: =_xlfn.MINIFS('225-50R18 (standard)'!$J$2:$J$33,'225-50R18 (standard)'!$A$2:$A$33,"All-weather 3PMSF") | C14: =4*B14 | D14: =INDEX('225-50R18 (standard)'!$B$2:$B$33,MATCH(1,INDEX(('225-50R18 (standard)'!$A$2:$A$33="All-weather 3PMSF")*('225-50R18 (standard)'!$J$2:$J$33=B14),0),0))&" "&INDEX('225-50R18 (standard)'!$C$2:$C$33,MATCH(1,INDEX(('225-50R18 (standard)'!$A$2:$A$33="All-weather 3PMSF")*('225-50R18 (standard)'!$J$2:$J$33=B14),0),0))&" — "&INDEX('225-50R18 (standard)'!$K$2:$K$33,MATCH(1,INDEX(('225-50R18 (standard)'!$A$2:$A$33="All-weather 3PMSF")*('225-50R18 (standard)'!$J$2:$J$33=B14),0),0))
A15: 225/50R18 · All-season | B15: =_xlfn.MINIFS('225-50R18 (standard)'!$J$2:$J$33,'225-50R18 (standard)'!$A$2:$A$33,"All-season") | C15: =4*B15 | D15: =INDEX('225-50R18 (standard)'!$B$2:$B$33,MATCH(1,INDEX(('225-50R18 (standard)'!$A$2:$A$33="All-season")*('225-50R18 (standard)'!$J$2:$J$33=B15),0),0))&" "&INDEX('225-50R18 (standard)'!$C$2:$C$33,MATCH(1,INDEX(('225-50R18 (standard)'!$A$2:$A$33="All-season")*('225-50R18 (standard)'!$J$2:$J$33=B15),0),0))&" — "&INDEX('225-50R18 (standard)'!$K$2:$K$33,MATCH(1,INDEX(('225-50R18 (standard)'!$A$2:$A$33="All-season")*('225-50R18 (standard)'!$J$2:$J$33=B15),0),0))
A16: 225/45R19 · All-weather 3PMSF | B16: =_xlfn.MINIFS('225-45R19 (19in option)'!$J$2:$J$20,'225-45R19 (19in option)'!$A$2:$A$20,"All-weather 3PMSF") | C16: =4*B16 | D16: =INDEX('225-45R19 (19in option)'!$B$2:$B$20,MATCH(1,INDEX(('225-45R19 (19in option)'!$A$2:$A$20="All-weather 3PMSF")*('225-45R19 (19in option)'!$J$2:$J$20=B16),0),0))&" "&INDEX('225-45R19 (19in option)'!$C$2:$C$20,MATCH(1,INDEX(('225-45R19 (19in option)'!$A$2:$A$20="All-weather 3PMSF")*('225-45R19 (19in option)'!$J$2:$J$20=B16),0),0))&" — "&INDEX('225-45R19 (19in option)'!$K$2:$K$20,MATCH(1,INDEX(('225-45R19 (19in option)'!$A$2:$A$20="All-weather 3PMSF")*('225-45R19 (19in option)'!$J$2:$J$20=B16),0),0))
A17: 225/45R19 · All-season | B17: =_xlfn.MINIFS('225-45R19 (19in option)'!$J$2:$J$20,'225-45R19 (19in option)'!$A$2:$A$20,"All-season") | C17: =4*B17 | D17: =INDEX('225-45R19 (19in option)'!$B$2:$B$20,MATCH(1,INDEX(('225-45R19 (19in option)'!$A$2:$A$20="All-season")*('225-45R19 (19in option)'!$J$2:$J$20=B17),0),0))&" "&INDEX('225-45R19 (19in option)'!$C$2:$C$20,MATCH(1,INDEX(('225-45R19 (19in option)'!$A$2:$A$20="All-season")*('225-45R19 (19in option)'!$J$2:$J$20=B17),0),0))&" — "&INDEX('225-45R19 (19in option)'!$K$2:$K$20,MATCH(1,INDEX(('225-45R19 (19in option)'!$A$2:$A$20="All-season")*('225-45R19 (19in option)'!$J$2:$J$20=B17),0),0))
A19: Recommendation (one line per option)
A20: Michelin CrossClimate 2 (18") | B20: Best-known all-weather benchmark; CAD $321.95 at BC/PMC/Kal, stack 10% code at BC + $100 Michelin rebate. Not stocked in 225/45R19 anywhere checked.
A21: Pirelli Cinturato WeatherActive (18") | B21: Cheapest 3PMSF 18" at CAD $245.97 (Blackcircles, 76 in stock) — but $80/tire more at Point S; buy online.
A22: Toyo Celsius II (18") | B22: Mid-price all-weather at CAD $281.00, identical at BC and PMC.
A23: Nitto Motivo 365 (19") | B23: Cheapest and most widely stocked 3PMSF in 225/45R19 (CAD $273.70 BC); only option carried by all four priced retailers in 19".
A24: Goodyear WeatherReady 2 (19") | B24: Premium-brand 3PMSF in 19", but CAD $408.99+ — $135.29/tire over the Nitto.
A25: Continental DWS06 Plus / Michelin Defender2 (all-season) | B25: If you run separate winters: DWS06 Plus CAD $275.99 (18") / $297.99 (19"); Defender2 CAD $278.95 (18") for tread life.

Sheet 225-50R18 (standard)
A1: Category | B1: Brand | C1: Model | D1: Load / speed (OE-or-better) | E1: Blackcircles.ca | F1: PMCtire.com | G1: Kal Tire | H1: Point S | I1: Costco | J1: Lowest CAD $/tire | K1: Lowest at | L1: Set of 4 at lowest (CAD $) | M1: # retailers priced | N1: Verif | O1: Notes / promos (per tire prices exclude mail-in rebates)
A2: All-weather 3PMSF | B2: Michelin | C2: CrossClimate 2 | D2: 95H | E2: 321.95 | F2: 321.95 | G2: 321.95 | H2: 333.99 | I2: Member price | J2: =IF(COUNT(E2:I2)=0,"Not published",MIN(E2:I2)) | K2: =IF(COUNT(E2:I2)=0,"n/a",INDEX($E$1:$I$1,MATCH(MIN(E2:I2),E2:I2,0))&IF(COUNTIF(E2:I2,MIN(E2:I2))>1," (tie x"&COUNTIF(E2:I2,MIN(E2:I2))&")","")) | L2: =IF(COUNT(E2:I2)=0,"n/a",4*MIN(E2:I2)) | M2: =COUNT(E2:I2) | N2: [V] | O2: Michelin mail-in up to $100 / set of 4, Sep 21–Dec 18; BC code PROMOCC2 10%
A3: All-weather 3PMSF | B3: Goodyear | C3: Assurance WeatherReady 2 | D3: 95V | E3: 305.99 | F3: 310.24 | G3: Not listed | H3: 318.99 | I3: Not listed | J3: =IF(COUNT(E3:I3)=0,"Not published",MIN(E3:I3)) | K3: =IF(COUNT(E3:I3)=0,"n/a",INDEX($E$1:$I$1,MATCH(MIN(E3:I3),E3:I3,0))&IF(COUNTIF(E3:I3,MIN(E3:I3))>1," (tie x"&COUNTIF(E3:I3,MIN(E3:I3))&")","")) | L3: =IF(COUNT(E3:I3)=0,"n/a",4*MIN(E3:I3)) | M3: =COUNT(E3:I3) | N3: [V] | O3: Goodyear mail-in up to $100 / set, Sep 7–Dec 20
A4: All-weather 3PMSF | B4: Toyo | C4: Celsius II | D4: 95V | E4: 281 | F4: 281 | G4: Not listed | H4: 297.99 | I4: Not listed | J4: =IF(COUNT(E4:I4)=0,"Not published",MIN(E4:I4)) | K4: =IF(COUNT(E4:I4)=0,"n/a",INDEX($E$1:$I$1,MATCH(MIN(E4:I4),E4:I4,0))&IF(COUNTIF(E4:I4,MIN(E4:I4))>1," (tie x"&COUNTIF(E4:I4,MIN(E4:I4))&")","")) | L4: =IF(COUNT(E4:I4)=0,"n/a",4*MIN(E4:I4)) | M4: =COUNT(E4:I4) | N4: [V] | O4: Toyo mail-in $80–100 / set, Sep 12–Dec 19
A5: All-weather 3PMSF | B5: Bridgestone | C5: WeatherPeak | D5: 95H | E5: 278.19 | F5: 278.59 | G5: Not listed | H5: Not listed | I5: Not listed | J5: =IF(COUNT(E5:I5)=0,"Not published",MIN(E5:I5)) | K5: =IF(COUNT(E5:I5)=0,"n/a",INDEX($E$1:$I$1,MATCH(MIN(E5:I5),E5:I5,0))&IF(COUNTIF(E5:I5,MIN(E5:I5))>1," (tie x"&COUNTIF(E5:I5,MIN(E5:I5))&")","")) | L5: =IF(COUNT(E5:I5)=0,"n/a",4*MIN(E5:I5)) | M5: =COUNT(E5:I5) | N5: [V] | O5: BC code WPEAK 12%; not listed at Kal / Point S / Costco
A6: All-weather 3PMSF | B6: Vredestein | C6: Quatrac Pro+ | D6: 99W XL | E6: 279.31 | F6: 273.86 | G6: Not listed | H6: Not listed | I6: Not listed | J6: =IF(COUNT(E6:I6)=0,"Not published",MIN(E6:I6)) | K6: =IF(COUNT(E6:I6)=0,"n/a",INDEX($E$1:$I$1,MATCH(MIN(E6:I6),E6:I6,0))&IF(COUNTIF(E6:I6,MIN(E6:I6))>1," (tie x"&COUNTIF(E6:I6,MIN(E6:I6))&")","")) | L6: =IF(COUNT(E6:I6)=0,"n/a",4*MIN(E6:I6)) | M6: =COUNT(E6:I6) | N6: [V]
A7: All-weather 3PMSF | B7: Firestone | C7: WeatherGrip | D7: 95H | E7: 259.71 | F7: 256.99 | G7: 277.92 | H7: 273.99 | I7: Not listed | J7: =IF(COUNT(E7:I7)=0,"Not published",MIN(E7:I7)) | K7: =IF(COUNT(E7:I7)=0,"n/a",INDEX($E$1:$I$1,MATCH(MIN(E7:I7),E7:I7,0))&IF(COUNTIF(E7:I7,MIN(E7:I7))>1," (tie x"&COUNTIF(E7:I7,MIN(E7:I7))&")","")) | L7: =IF(COUNT(E7:I7)=0,"n/a",4*MIN(E7:I7)) | M7: =COUNT(E7:I7) | N7: [V] | O7: Firestone mail-in $70 / set, Sep 14/15–Dec 7
A8: All-weather 3PMSF | B8: General | C8: AltiMAX 365AW | D8: 95H | E8: 247.99 | F8: 252.99 | G8: Not listed | H8: 266.99 | I8: Not listed | J8: =IF(COUNT(E8:I8)=0,"Not published",MIN(E8:I8)) | K8: =IF(COUNT(E8:I8)=0,"n/a",INDEX($E$1:$I$1,MATCH(MIN(E8:I8),E8:I8,0))&IF(COUNTIF(E8:I8,MIN(E8:I8))>1," (tie x"&COUNTIF(E8:I8,MIN(E8:I8))&")","")) | L8: =IF(COUNT(E8:I8)=0,"n/a",4*MIN(E8:I8)) | M8: =COUNT(E8:I8) | N8: [V] | O8: General mail-in $50 / set
A9: All-weather 3PMSF | B9: Pirelli | C9: Cinturato WeatherActive | D9: 95V | E9: 245.97 | F9: 278.53 | G9: 325.19 | H9: 325.99 | I9: Out of stock | J9: =IF(COUNT(E9:I9)=0,"Not published",MIN(E9:I9)) | K9: =IF(COUNT(E9:I9)=0,"n/a",INDEX($E$1:$I$1,MATCH(MIN(E9:I9),E9:I9,0))&IF(COUNTIF(E9:I9,MIN(E9:I9))>1," (tie x"&COUNTIF(E9:I9,MIN(E9:I9))&")","")) | L9: =IF(COUNT(E9:I9)=0,"n/a",4*MIN(E9:I9)) | M9: =COUNT(E9:I9) | N9: [V] | O9: Widest spread in the set: $80.02/tire between Blackcircles and Point S
A10: All-weather 3PMSF | B10: Nokian | C10: Remedy WRG5 | D10: 99V XL | E10: Not listed | F10: Not listed | G10: 287.44 | H10: 324.99 | I10: Not listed | J10: =IF(COUNT(E10:I10)=0,"Not published",MIN(E10:I10)) | K10: =IF(COUNT(E10:I10)=0,"n/a",INDEX($E$1:$I$1,MATCH(MIN(E10:I10),E10:I10,0))&IF(COUNTIF(E10:I10,MIN(E10:I10))>1," (tie x"&COUNTIF(E10:I10,MIN(E10:I10))&")","")) | L10: =IF(COUNT(E10:I10)=0,"n/a",4*MIN(E10:I10)) | M10: =COUNT(E10:I10) | N10: [V] | O10: Kal price is a sale (was $299.94) + $50 instant off set, Sep 14–Dec 20; out of stock at PMC
A11: All-weather 3PMSF | B11: Nitto | C11: Motivo 365 | D11: 99W XL | E11: Not listed | F11: Not listed | G11: 269.08 | H11: 266.99 | I11: Not listed | J11: =IF(COUNT(E11:I11)=0,"Not published",MIN(E11:I11)) | K11: =IF(COUNT(E11:I11)=0,"n/a",INDEX($E$1:$I$1,MATCH(MIN(E11:I11),E11:I11,0))&IF(COUNTIF(E11:I11,MIN(E11:I11))>1," (tie x"&COUNTIF(E11:I11,MIN(E11:I11))&")","")) | L11: =IF(COUNT(E11:I11)=0,"n/a",4*MIN(E11:I11)) | M11: =COUNT(E11:I11) | N11: [V] | O11: Kal price is a sale (was $284.08) + $60 off set; Nitto rebate $60 at Point S
A12: All-weather 3PMSF | B12: Toyo | C12: Celsius Sport | D12: 95V | E12: Not listed | F12: Not listed | G12: Not listed | H12: 297.99 | I12: Not listed | J12: =IF(COUNT(E12:I12)=0,"Not published",MIN(E12:I12)) | K12: =IF(COUNT(E12:I12)=0,"n/a",INDEX($E$1:$I$1,MATCH(MIN(E12:I12),E12:I12,0))&IF(COUNTIF(E12:I12,MIN(E12:I12))>1," (tie x"&COUNTIF(E12:I12,MIN(E12:I12))&")","")) | L12: =IF(COUNT(E12:I12)=0,"n/a",4*MIN(E12:I12)) | M12: =COUNT(E12:I12) | N12: [V] | O12: Toyo mail-in up to $80
A13: All-weather 3PMSF | B13: Bridgestone | C13: UltraWeather | D13: 99V XL | E13: Not listed | F13: Not listed | G13: Not listed | H13: 329.99 | I13: Member price | J13: =IF(COUNT(E13:I13)=0,"Not published",MIN(E13:I13)) | K13: =IF(COUNT(E13:I13)=0,"n/a",INDEX($E$1:$I$1,MATCH(MIN(E13:I13),E13:I13,0))&IF(COUNTIF(E13:I13,MIN(E13:I13))>1," (tie x"&COUNTIF(E13:I13,MIN(E13:I13))&")","")) | L13: =IF(COUNT(E13:I13)=0,"n/a",4*MIN(E13:I13)) | M13: =COUNT(E13:I13) | N13: [V] | O13: Bridgestone mail-in up to $100
A14: All-weather 3PMSF | B14: Falken | C14: Aklimate | D14: 95V | E14: Not listed | F14: Not listed | G14: Not listed | H14: 268.99 | I14: Not listed | J14: =IF(COUNT(E14:I14)=0,"Not published",MIN(E14:I14)) | K14: =IF(COUNT(E14:I14)=0,"n/a",INDEX($E$1:$I$1,MATCH(MIN(E14:I14),E14:I14,0))&IF(COUNTIF(E14:I14,MIN(E14:I14))>1," (tie x"&COUNTIF(E14:I14,MIN(E14:I14))&")","")) | L14: =IF(COUNT(E14:I14)=0,"n/a",4*MIN(E14:I14)) | M14: =COUNT(E14:I14) | N14: [V] | O14: PMC lists Falken $80 rebate from Oct 1
A15: All-weather 3PMSF | B15: Cooper | C15: TractionCommand | D15: 95V | E15: Not listed | F15: Not listed | G15: Not listed | H15: 261.99 | I15: Not listed | J15: =IF(COUNT(E15:I15)=0,"Not published",MIN(E15:I15)) | K15: =IF(COUNT(E15:I15)=0,"n/a",INDEX($E$1:$I$1,MATCH(MIN(E15:I15),E15:I15,0))&IF(COUNTIF(E15:I15,MIN(E15:I15))>1," (tie x"&COUNTIF(E15:I15,MIN(E15:I15))&")","")) | L15: =IF(COUNT(E15:I15)=0,"n/a",4*MIN(E15:I15)) | M15: =COUNT(E15:I15) | N15: [V]
A16: All-season | B16: Michelin | C16: Defender2 | D16: 99V XL | E16: 278.95 | F16: 278.95 | G16: Not listed | H16: 287.99 | I16: Member price | J16: =IF(COUNT(E16:I16)=0,"Not published",MIN(E16:I16)) | K16: =IF(COUNT(E16:I16)=0,"n/a",INDEX($E$1:$I$1,MATCH(MIN(E16:I16),E16:I16,0))&IF(COUNTIF(E16:I16,MIN(E16:I16))>1," (tie x"&COUNTIF(E16:I16,MIN(E16:I16))&")","")) | L16: =IF(COUNT(E16:I16)=0,"n/a",4*MIN(E16:I16)) | M16: =COUNT(E16:I16) | N16: [V] | O16: Michelin mail-in up to $100; BC code PROMODEFENDER2 10%
A17: All-season | B17: Michelin | C17: Defender 2 CUV (Kal Tire listing name) | D17: 99V | E17: Not listed | F17: Not listed | G17: 278.95 | H17: Not listed | I17: Not listed | J17: =IF(COUNT(E17:I17)=0,"Not published",MIN(E17:I17)) | K17: =IF(COUNT(E17:I17)=0,"n/a",INDEX($E$1:$I$1,MATCH(MIN(E17:I17),E17:I17,0))&IF(COUNTIF(E17:I17,MIN(E17:I17))>1," (tie x"&COUNTIF(E17:I17,MIN(E17:I17))&")","")) | L17: =IF(COUNT(E17:I17)=0,"n/a",4*MIN(E17:I17)) | M17: =COUNT(E17:I17) | N17: [V] | O17: Kept separate: Kal names it 'CUV'; same price as Defender2 elsewhere — not confirmed identical
A18: All-season | B18: Michelin | C18: Pilot Sport All Season 4 | D18: 99Y XL | E18: 286.95 | F18: 286.95 | G18: Not listed | H18: Not listed | I18: Not listed | J18: =IF(COUNT(E18:I18)=0,"Not published",MIN(E18:I18)) | K18: =IF(COUNT(E18:I18)=0,"n/a",INDEX($E$1:$I$1,MATCH(MIN(E18:I18),E18:I18,0))&IF(COUNTIF(E18:I18,MIN(E18:I18))>1," (tie x"&COUNTIF(E18:I18,MIN(E18:I18))&")","")) | L18: =IF(COUNT(E18:I18)=0,"n/a",4*MIN(E18:I18)) | M18: =COUNT(E18:I18) | N18: [V] | O18: Performance all-season; BC code AS4PROMO 15%
A19: All-season | B19: Continental | C19: ExtremeContact DWS06 Plus | D19: 95W | E19: 275.99 | F19: 275.99 | G19: Not listed | H19: 288.99 | I19: Not listed | J19: =IF(COUNT(E19:I19)=0,"Not published",MIN(E19:I19)) | K19: =IF(COUNT(E19:I19)=0,"n/a",INDEX($E$1:$I$1,MATCH(MIN(E19:I19),E19:I19,0))&IF(COUNTIF(E19:I19,MIN(E19:I19))>1," (tie x"&COUNTIF(E19:I19,MIN(E19:I19))&")","")) | L19: =IF(COUNT(E19:I19)=0,"n/a",4*MIN(E19:I19)) | M19: =COUNT(E19:I19) | N19: [V] | O19: BC code PROMODWS06 12%; Continental rebate $60–110
A20: All-season | B20: Continental | C20: TrueContact Tour 54 | D20: 95H | E20: 251.99 | F20: 251.99 | G20: Not listed | H20: 266.99 | I20: Not listed | J20: =IF(COUNT(E20:I20)=0,"Not published",MIN(E20:I20)) | K20: =IF(COUNT(E20:I20)=0,"n/a",INDEX($E$1:$I$1,MATCH(MIN(E20:I20),E20:I20,0))&IF(COUNTIF(E20:I20,MIN(E20:I20))>1," (tie x"&COUNTIF(E20:I20,MIN(E20:I20))&")","")) | L20: =IF(COUNT(E20:I20)=0,"n/a",4*MIN(E20:I20)) | M20: =COUNT(E20:I20) | N20: [V] | O20: BC code TOUR54 12%
A21: All-season | B21: Continental | C21: ProContact TX | D21: 95V | E21: Not listed | F21: Not listed | G21: 280.91 | H21: Not listed | I21: Not listed | J21: =IF(COUNT(E21:I21)=0,"Not published",MIN(E21:I21)) | K21: =IF(COUNT(E21:I21)=0,"n/a",INDEX($E$1:$I$1,MATCH(MIN(E21:I21),E21:I21,0))&IF(COUNTIF(E21:I21,MIN(E21:I21))>1," (tie x"&COUNTIF(E21:I21,MIN(E21:I21))&")","")) | L21: =IF(COUNT(E21:I21)=0,"n/a",4*MIN(E21:I21)) | M21: =COUNT(E21:I21) | N21: [V] | O21: Continental mail-in $60
A22: All-season | B22: Bridgestone | C22: Turanza EverDrive | D22: 99V XL | E22: 263.99 | F22: 263.99 | G22: Not listed | H22: 271.99 | I22: Member price | J22: =IF(COUNT(E22:I22)=0,"Not published",MIN(E22:I22)) | K22: =IF(COUNT(E22:I22)=0,"n/a",INDEX($E$1:$I$1,MATCH(MIN(E22:I22),E22:I22,0))&IF(COUNTIF(E22:I22,MIN(E22:I22))>1," (tie x"&COUNTIF(E22:I22,MIN(E22:I22))&")","")) | L22: =IF(COUNT(E22:I22)=0,"n/a",4*MIN(E22:I22)) | M22: =COUNT(E22:I22) | N22: [V] | O22: Bridgestone mail-in up to $100
A23: All-season | B23: Bridgestone | C23: Turanza LS100 | D23: 95H | E23: Not listed | F23: Not listed | G23: Not listed | H23: Not listed | I23: 359.99 | J23: =IF(COUNT(E23:I23)=0,"Not published",MIN(E23:I23)) | K23: =IF(COUNT(E23:I23)=0,"n/a",INDEX($E$1:$I$1,MATCH(MIN(E23:I23),E23:I23,0))&IF(COUNTIF(E23:I23,MIN(E23:I23))>1," (tie x"&COUNTIF(E23:I23,MIN(E23:I23))&")","")) | L23: =IF(COUNT(E23:I23)=0,"n/a",4*MIN(E23:I23)) | M23: =COUNT(E23:I23) | N23: [V] | O23: Costco: OE fitment on VW per site; $100 off set of 4 to Oct 4; install included
A24: All-season | B24: Bridgestone | C24: Potenza RE97AS | D24: 95H | E24: Not listed | F24: Not listed | G24: Not listed | H24: Not listed | I24: 324.99 | J24: =IF(COUNT(E24:I24)=0,"Not published",MIN(E24:I24)) | K24: =IF(COUNT(E24:I24)=0,"n/a",INDEX($E$1:$I$1,MATCH(MIN(E24:I24),E24:I24,0))&IF(COUNTIF(E24:I24,MIN(E24:I24))>1," (tie x"&COUNTIF(E24:I24,MIN(E24:I24))&")","")) | L24: =IF(COUNT(E24:I24)=0,"n/a",4*MIN(E24:I24)) | M24: =COUNT(E24:I24) | N24: [V] | O24: Costco: $100 off set of 4 to Oct 4; install included
A25: All-season | B25: Bridgestone | C25: Potenza RE980AS+ | D25: 95W | E25: Not listed | F25: Not listed | G25: 249.13 | H25: Not listed | I25: Not listed | J25: =IF(COUNT(E25:I25)=0,"Not published",MIN(E25:I25)) | K25: =IF(COUNT(E25:I25)=0,"n/a",INDEX($E$1:$I$1,MATCH(MIN(E25:I25),E25:I25,0))&IF(COUNTIF(E25:I25,MIN(E25:I25))>1," (tie x"&COUNTIF(E25:I25,MIN(E25:I25))&")","")) | L25: =IF(COUNT(E25:I25)=0,"n/a",4*MIN(E25:I25)) | M25: =COUNT(E25:I25) | N25: [V] | O25: Kal: price from product data only; stock/promo not checked
A26: All-season | B26: Pirelli | C26: P7 All Season Plus 3 | D26: 95V | E26: 255.78 | F26: 255.78 | G26: 264.1 | H26: Not listed | I26: Not listed | J26: =IF(COUNT(E26:I26)=0,"Not published",MIN(E26:I26)) | K26: =IF(COUNT(E26:I26)=0,"n/a",INDEX($E$1:$I$1,MATCH(MIN(E26:I26),E26:I26,0))&IF(COUNTIF(E26:I26,MIN(E26:I26))>1," (tie x"&COUNTIF(E26:I26,MIN(E26:I26))&")","")) | L26: =IF(COUNT(E26:I26)=0,"n/a",4*MIN(E26:I26)) | M26: =COUNT(E26:I26) | N26: [V] | O26: BC code P7ASPLUS3 10%
A27: All-season | B27: Pirelli | C27: P Zero All Season Plus 3 | D27: 95Y | E27: Not listed | F27: Not listed | G27: 265.89 | H27: Not listed | I27: Not listed | J27: =IF(COUNT(E27:I27)=0,"Not published",MIN(E27:I27)) | K27: =IF(COUNT(E27:I27)=0,"n/a",INDEX($E$1:$I$1,MATCH(MIN(E27:I27),E27:I27,0))&IF(COUNTIF(E27:I27,MIN(E27:I27))>1," (tie x"&COUNTIF(E27:I27,MIN(E27:I27))&")","")) | L27: =IF(COUNT(E27:I27)=0,"n/a",4*MIN(E27:I27)) | M27: =COUNT(E27:I27) | N27: [V]
A28: All-season | B28: Pirelli | C28: Cinturato P7 All Season | D28: 95V | E28: Not listed | F28: Not listed | G28: Not listed | H28: 315.99 | I28: Not listed | J28: =IF(COUNT(E28:I28)=0,"Not published",MIN(E28:I28)) | K28: =IF(COUNT(E28:I28)=0,"n/a",INDEX($E$1:$I$1,MATCH(MIN(E28:I28),E28:I28,0))&IF(COUNTIF(E28:I28,MIN(E28:I28))>1," (tie x"&COUNTIF(E28:I28,MIN(E28:I28))&")","")) | L28: =IF(COUNT(E28:I28)=0,"n/a",4*MIN(E28:I28)) | M28: =COUNT(E28:I28) | N28: [V] | O28: Older model than P7 AS Plus 3
A29: All-season | B29: Goodyear | C29: Assurance MaxLife 2 | D29: 99V XL | E29: 246.77 | F29: 259.39 | G29: Not listed | H29: 271.99 | I29: Not listed | J29: =IF(COUNT(E29:I29)=0,"Not published",MIN(E29:I29)) | K29: =IF(COUNT(E29:I29)=0,"n/a",INDEX($E$1:$I$1,MATCH(MIN(E29:I29),E29:I29,0))&IF(COUNTIF(E29:I29,MIN(E29:I29))>1," (tie x"&COUNTIF(E29:I29,MIN(E29:I29))&")","")) | L29: =IF(COUNT(E29:I29)=0,"n/a",4*MIN(E29:I29)) | M29: =COUNT(E29:I29) | N29: [V] | O29: Goodyear mail-in $60 (PMC)
A30: All-season | B30: Goodyear | C30: Assurance ComfortDrive | D30: 95V | E30: Not listed | F30: Not listed | G30: Not listed | H30: 272.99 | I30: Not listed | J30: =IF(COUNT(E30:I30)=0,"Not published",MIN(E30:I30)) | K30: =IF(COUNT(E30:I30)=0,"n/a",INDEX($E$1:$I$1,MATCH(MIN(E30:I30),E30:I30,0))&IF(COUNTIF(E30:I30,MIN(E30:I30))>1," (tie x"&COUNTIF(E30:I30,MIN(E30:I30))&")","")) | L30: =IF(COUNT(E30:I30)=0,"n/a",4*MIN(E30:I30)) | M30: =COUNT(E30:I30) | N30: [V]
A31: All-season | B31: Firestone | C31: Firehawk AS V2 | D31: 95W | E31: Not listed | F31: Not listed | G31: 248.96 | H31: 245.99 | I31: Member price | J31: =IF(COUNT(E31:I31)=0,"Not published",MIN(E31:I31)) | K31: =IF(COUNT(E31:I31)=0,"n/a",INDEX($E$1:$I$1,MATCH(MIN(E31:I31),E31:I31,0))&IF(COUNTIF(E31:I31,MIN(E31:I31))>1," (tie x"&COUNTIF(E31:I31,MIN(E31:I31))&")","")) | L31: =IF(COUNT(E31:I31)=0,"n/a",4*MIN(E31:I31)) | M31: =COUNT(E31:I31) | N31: [V] | O31: Firestone mail-in $60
A32: All-season | B32: Nokian | C32: Surpass AS01 | D32: 99W | E32: Not listed | F32: Not listed | G32: 239.11 | H32: Not listed | I32: Not listed | J32: =IF(COUNT(E32:I32)=0,"Not published",MIN(E32:I32)) | K32: =IF(COUNT(E32:I32)=0,"n/a",INDEX($E$1:$I$1,MATCH(MIN(E32:I32),E32:I32,0))&IF(COUNTIF(E32:I32,MIN(E32:I32))>1," (tie x"&COUNTIF(E32:I32,MIN(E32:I32))&")","")) | L32: =IF(COUNT(E32:I32)=0,"n/a",4*MIN(E32:I32)) | M32: =COUNT(E32:I32) | N32: [V]
A33: All-season | B33: Nokian | C33: One | D33: 99V | E33: Not listed | F33: Not listed | G33: 236.19 | H33: Not listed | I33: Not listed | J33: =IF(COUNT(E33:I33)=0,"Not published",MIN(E33:I33)) | K33: =IF(COUNT(E33:I33)=0,"n/a",INDEX($E$1:$I$1,MATCH(MIN(E33:I33),E33:I33,0))&IF(COUNTIF(E33:I33,MIN(E33:I33))>1," (tie x"&COUNTIF(E33:I33,MIN(E33:I33))&")","")) | L33: =IF(COUNT(E33:I33)=0,"n/a",4*MIN(E33:I33)) | M33: =COUNT(E33:I33) | N33: [V] | O33: Lowest priced tire found in 225/50R18

Sheet 225-45R19 (19in option)
A1: Category | B1: Brand | C1: Model | D1: Load / speed (OE-or-better) | E1: Blackcircles.ca | F1: PMCtire.com | G1: Kal Tire | H1: Point S | I1: Costco | J1: Lowest CAD $/tire | K1: Lowest at | L1: Set of 4 at lowest (CAD $) | M1: # retailers priced | N1: Verif | O1: Notes / promos (per tire prices exclude mail-in rebates)
A2: All-weather 3PMSF | B2: Goodyear | C2: Assurance WeatherReady 2 | D2: 96W XL | E2: 408.99 | F2: Out of stock | G2: Not listed | H2: 425.99 | I2: Not listed | J2: =IF(COUNT(E2:I2)=0,"Not published",MIN(E2:I2)) | K2: =IF(COUNT(E2:I2)=0,"n/a",INDEX($E$1:$I$1,MATCH(MIN(E2:I2),E2:I2,0))&IF(COUNTIF(E2:I2,MIN(E2:I2))>1," (tie x"&COUNTIF(E2:I2,MIN(E2:I2))&")","")) | L2: =IF(COUNT(E2:I2)=0,"n/a",4*MIN(E2:I2)) | M2: =COUNT(E2:I2) | N2: [V] | O2: PMC lists at $408.99 but out of stock; Goodyear mail-in up to $100
A3: All-weather 3PMSF | B3: Toyo | C3: Celsius Sport | D3: 96W XL | E3: 332 | F3: Out of stock | G3: Not listed | H3: 350.99 | I3: Not listed | J3: =IF(COUNT(E3:I3)=0,"Not published",MIN(E3:I3)) | K3: =IF(COUNT(E3:I3)=0,"n/a",INDEX($E$1:$I$1,MATCH(MIN(E3:I3),E3:I3,0))&IF(COUNTIF(E3:I3,MIN(E3:I3))>1," (tie x"&COUNTIF(E3:I3,MIN(E3:I3))&")","")) | L3: =IF(COUNT(E3:I3)=0,"n/a",4*MIN(E3:I3)) | M3: =COUNT(E3:I3) | N3: [V] | O3: PMC lists at $332.00 but out of stock; BC has 3 in stock
A4: All-weather 3PMSF | B4: Vredestein | C4: Quatrac Pro+ | D4: 96W XL | E4: 310.58 | F4: 287.98 | G4: Not listed | H4: Not listed | I4: Not listed | J4: =IF(COUNT(E4:I4)=0,"Not published",MIN(E4:I4)) | K4: =IF(COUNT(E4:I4)=0,"n/a",INDEX($E$1:$I$1,MATCH(MIN(E4:I4),E4:I4,0))&IF(COUNTIF(E4:I4,MIN(E4:I4))>1," (tie x"&COUNTIF(E4:I4,MIN(E4:I4))&")","")) | L4: =IF(COUNT(E4:I4)=0,"n/a",4*MIN(E4:I4)) | M4: =COUNT(E4:I4) | N4: [V]
A5: All-weather 3PMSF | B5: Nitto | C5: Motivo 365 | D5: 96W XL | E5: 273.7 | F5: 275.73 | G5: 294.1 | H5: 290.99 | I5: Not listed | J5: =IF(COUNT(E5:I5)=0,"Not published",MIN(E5:I5)) | K5: =IF(COUNT(E5:I5)=0,"n/a",INDEX($E$1:$I$1,MATCH(MIN(E5:I5),E5:I5,0))&IF(COUNTIF(E5:I5,MIN(E5:I5))>1," (tie x"&COUNTIF(E5:I5,MIN(E5:I5))&")","")) | L5: =IF(COUNT(E5:I5)=0,"n/a",4*MIN(E5:I5)) | M5: =COUNT(E5:I5) | N5: [V] | O5: Kal price is a sale (was $309.10) + $60 off set; Nitto rebate $60–70
A6: All-weather 3PMSF | B6: Falken | C6: Aklimate | D6: 96W XL | E6: Not listed | F6: Not listed | G6: Not listed | H6: 295.99 | I6: Not listed | J6: =IF(COUNT(E6:I6)=0,"Not published",MIN(E6:I6)) | K6: =IF(COUNT(E6:I6)=0,"n/a",INDEX($E$1:$I$1,MATCH(MIN(E6:I6),E6:I6,0))&IF(COUNTIF(E6:I6,MIN(E6:I6))>1," (tie x"&COUNTIF(E6:I6,MIN(E6:I6))&")","")) | L6: =IF(COUNT(E6:I6)=0,"n/a",4*MIN(E6:I6)) | M6: =COUNT(E6:I6) | N6: [V] | O6: PMC lists Falken $80 rebate from Oct 1
A7: All-season | B7: Michelin | C7: Pilot Sport All Season 4 | D7: 96Y XL | E7: 325.95 | F7: 325.95 | G7: Not listed | H7: Not listed | I7: Member price | J7: =IF(COUNT(E7:I7)=0,"Not published",MIN(E7:I7)) | K7: =IF(COUNT(E7:I7)=0,"n/a",INDEX($E$1:$I$1,MATCH(MIN(E7:I7),E7:I7,0))&IF(COUNTIF(E7:I7,MIN(E7:I7))>1," (tie x"&COUNTIF(E7:I7,MIN(E7:I7))&")","")) | L7: =IF(COUNT(E7:I7)=0,"n/a",4*MIN(E7:I7)) | M7: =COUNT(E7:I7) | N7: [V] | O7: BC code AS4PROMO 15%; Michelin mail-in up to $100
A8: All-season | B8: Continental | C8: ExtremeContact DWS06 Plus | D8: 92W | E8: 297.99 | F8: 297.99 | G8: Not listed | H8: 315.99 | I8: Not listed | J8: =IF(COUNT(E8:I8)=0,"Not published",MIN(E8:I8)) | K8: =IF(COUNT(E8:I8)=0,"n/a",INDEX($E$1:$I$1,MATCH(MIN(E8:I8),E8:I8,0))&IF(COUNTIF(E8:I8,MIN(E8:I8))>1," (tie x"&COUNTIF(E8:I8,MIN(E8:I8))&")","")) | L8: =IF(COUNT(E8:I8)=0,"n/a",4*MIN(E8:I8)) | M8: =COUNT(E8:I8) | N8: [V] | O8: BC code PROMODWS06 12%
A9: All-season | B9: Bridgestone | C9: Potenza Sport A/S | D9: 96W XL | E9: 308.99 | F9: 308.99 | G9: Not listed | H9: 318.99 | I9: Not listed | J9: =IF(COUNT(E9:I9)=0,"Not published",MIN(E9:I9)) | K9: =IF(COUNT(E9:I9)=0,"n/a",INDEX($E$1:$I$1,MATCH(MIN(E9:I9),E9:I9,0))&IF(COUNTIF(E9:I9,MIN(E9:I9))>1," (tie x"&COUNTIF(E9:I9,MIN(E9:I9))&")","")) | L9: =IF(COUNT(E9:I9)=0,"n/a",4*MIN(E9:I9)) | M9: =COUNT(E9:I9) | N9: [V] | O9: Bridgestone mail-in $70
A10: All-season | B10: Bridgestone | C10: Potenza RE980AS+ | D10: 96W | E10: Not listed | F10: Not listed | G10: 295.3 | H10: Not listed | I10: Not listed | J10: =IF(COUNT(E10:I10)=0,"Not published",MIN(E10:I10)) | K10: =IF(COUNT(E10:I10)=0,"n/a",INDEX($E$1:$I$1,MATCH(MIN(E10:I10),E10:I10,0))&IF(COUNTIF(E10:I10,MIN(E10:I10))>1," (tie x"&COUNTIF(E10:I10,MIN(E10:I10))&")","")) | L10: =IF(COUNT(E10:I10)=0,"n/a",4*MIN(E10:I10)) | M10: =COUNT(E10:I10) | N10: [V] | O10: Kal: price from product data only; stock/promo not checked
A11: All-season | B11: Bridgestone | C11: Ecopia H/L 422 Plus | D11: 92W | E11: Not listed | F11: Not listed | G11: Not listed | H11: Not listed | I11: 444.99 | J11: =IF(COUNT(E11:I11)=0,"Not published",MIN(E11:I11)) | K11: =IF(COUNT(E11:I11)=0,"n/a",INDEX($E$1:$I$1,MATCH(MIN(E11:I11),E11:I11,0))&IF(COUNTIF(E11:I11,MIN(E11:I11))>1," (tie x"&COUNTIF(E11:I11,MIN(E11:I11))&")","")) | L11: =IF(COUNT(E11:I11)=0,"n/a",4*MIN(E11:I11)) | M11: =COUNT(E11:I11) | N11: [V] | O11: Costco: $100 off set of 4 to Oct 4; install included
A12: All-season | B12: Pirelli | C12: P Zero All Season Plus 3 | D12: 96Y | E12: 277.82 | F12: Not listed | G12: 286.86 | H12: Not listed | I12: Not listed | J12: =IF(COUNT(E12:I12)=0,"Not published",MIN(E12:I12)) | K12: =IF(COUNT(E12:I12)=0,"n/a",INDEX($E$1:$I$1,MATCH(MIN(E12:I12),E12:I12,0))&IF(COUNTIF(E12:I12,MIN(E12:I12))>1," (tie x"&COUNTIF(E12:I12,MIN(E12:I12))&")","")) | L12: =IF(COUNT(E12:I12)=0,"n/a",4*MIN(E12:I12)) | M12: =COUNT(E12:I12) | N12: [V] | O12: BC code PZEROPLUS3 10%
A13: All-season | B13: Goodyear | C13: Eagle F1 All Season | D13: 96Y XL | E13: 255.24 | F13: 301.59 | G13: Not listed | H13: Not listed | I13: Not listed | J13: =IF(COUNT(E13:I13)=0,"Not published",MIN(E13:I13)) | K13: =IF(COUNT(E13:I13)=0,"n/a",INDEX($E$1:$I$1,MATCH(MIN(E13:I13),E13:I13,0))&IF(COUNTIF(E13:I13,MIN(E13:I13))>1," (tie x"&COUNTIF(E13:I13,MIN(E13:I13))&")","")) | L13: =IF(COUNT(E13:I13)=0,"n/a",4*MIN(E13:I13)) | M13: =COUNT(E13:I13) | N13: [V] | O13: $46.35/tire gap between the two online sellers
A14: All-season | B14: Goodyear | C14: Assurance ComfortDrive | D14: 96W XL | E14: Not listed | F14: Not listed | G14: Not listed | H14: 347.99 | I14: Not listed | J14: =IF(COUNT(E14:I14)=0,"Not published",MIN(E14:I14)) | K14: =IF(COUNT(E14:I14)=0,"n/a",INDEX($E$1:$I$1,MATCH(MIN(E14:I14),E14:I14,0))&IF(COUNTIF(E14:I14,MIN(E14:I14))>1," (tie x"&COUNTIF(E14:I14,MIN(E14:I14))&")","")) | L14: =IF(COUNT(E14:I14)=0,"n/a",4*MIN(E14:I14)) | M14: =COUNT(E14:I14) | N14: [V]
A15: All-season | B15: Hankook | C15: Ventus S1 AS | D15: 96Y XL | E15: 257.18 | F15: 264.04 | G15: Not listed | H15: Not listed | I15: Not listed | J15: =IF(COUNT(E15:I15)=0,"Not published",MIN(E15:I15)) | K15: =IF(COUNT(E15:I15)=0,"n/a",INDEX($E$1:$I$1,MATCH(MIN(E15:I15),E15:I15,0))&IF(COUNTIF(E15:I15,MIN(E15:I15))>1," (tie x"&COUNTIF(E15:I15,MIN(E15:I15))&")","")) | L15: =IF(COUNT(E15:I15)=0,"n/a",4*MIN(E15:I15)) | M15: =COUNT(E15:I15) | N15: [V]
A16: All-season | B16: General | C16: G-MAX AS-07 | D16: 92W | E16: 247.99 | F16: 257.21 | G16: Not listed | H16: Not listed | I16: Not listed | J16: =IF(COUNT(E16:I16)=0,"Not published",MIN(E16:I16)) | K16: =IF(COUNT(E16:I16)=0,"n/a",INDEX($E$1:$I$1,MATCH(MIN(E16:I16),E16:I16,0))&IF(COUNTIF(E16:I16,MIN(E16:I16))>1," (tie x"&COUNTIF(E16:I16,MIN(E16:I16))&")","")) | L16: =IF(COUNT(E16:I16)=0,"n/a",4*MIN(E16:I16)) | M16: =COUNT(E16:I16) | N16: [V] | O16: Lowest priced tire found in 225/45R19
A17: All-season | B17: Firestone | C17: Firehawk AS V2 | D17: 96W | E17: Not listed | F17: Not listed | G17: 282.17 | H17: 277.99 | I17: Member price | J17: =IF(COUNT(E17:I17)=0,"Not published",MIN(E17:I17)) | K17: =IF(COUNT(E17:I17)=0,"n/a",INDEX($E$1:$I$1,MATCH(MIN(E17:I17),E17:I17,0))&IF(COUNTIF(E17:I17,MIN(E17:I17))>1," (tie x"&COUNTIF(E17:I17,MIN(E17:I17))&")","")) | L17: =IF(COUNT(E17:I17)=0,"n/a",4*MIN(E17:I17)) | M17: =COUNT(E17:I17) | N17: [V] | O17: Firestone mail-in $60
A18: All-season | B18: Nokian | C18: Surpass AS01 | D18: 96W | E18: Not listed | F18: Not listed | G18: 274.03 | H18: Not listed | I18: Not listed | J18: =IF(COUNT(E18:I18)=0,"Not published",MIN(E18:I18)) | K18: =IF(COUNT(E18:I18)=0,"n/a",INDEX($E$1:$I$1,MATCH(MIN(E18:I18),E18:I18,0))&IF(COUNTIF(E18:I18,MIN(E18:I18))>1," (tie x"&COUNTIF(E18:I18,MIN(E18:I18))&")","")) | L18: =IF(COUNT(E18:I18)=0,"n/a",4*MIN(E18:I18)) | M18: =COUNT(E18:I18) | N18: [V]
A19: All-season | B19: Toyo | C19: Extensa HP II | D19: 96W | E19: Not listed | F19: Not listed | G19: Not listed | H19: 277.99 | I19: Not listed | J19: =IF(COUNT(E19:I19)=0,"Not published",MIN(E19:I19)) | K19: =IF(COUNT(E19:I19)=0,"n/a",INDEX($E$1:$I$1,MATCH(MIN(E19:I19),E19:I19,0))&IF(COUNTIF(E19:I19,MIN(E19:I19))>1," (tie x"&COUNTIF(E19:I19,MIN(E19:I19))&")","")) | L19: =IF(COUNT(E19:I19)=0,"n/a",4*MIN(E19:I19)) | M19: =COUNT(E19:I19) | N19: [V]
A20: All-season | B20: BFGoodrich | C20: g-Force COMP-2 A/S Plus | D20: 96W XL | E20: Not listed | F20: Not listed | G20: Not listed | H20: Not listed | I20: 344.99 | J20: =IF(COUNT(E20:I20)=0,"Not published",MIN(E20:I20)) | K20: =IF(COUNT(E20:I20)=0,"n/a",INDEX($E$1:$I$1,MATCH(MIN(E20:I20),E20:I20,0))&IF(COUNTIF(E20:I20,MIN(E20:I20))>1," (tie x"&COUNTIF(E20:I20,MIN(E20:I20))&")","")) | L20: =IF(COUNT(E20:I20)=0,"n/a",4*MIN(E20:I20)) | M20: =COUNT(E20:I20) | N20: [V] | O20: Costco: install included

Sheet Retailer terms
A1: Retailer | B1: Price basis | C1: Installation | D1: Shipping | E1: Location priced | F1: Site-wide promo | G1: Verif
A2: Blackcircles.ca | B2: Per tire, online | C2: Not included | D2: Free on most orders; fees for remote areas or out-of-province stock | E2: Online (national) | F2: Brand codes 10–15% on 4 tires, not combinable; FALL10 up to 10%. No end dates published | G2: [V]
A3: PMCtire.com | B3: Per tire, online | C3: Not included | D3: Free on 4+ tires 'almost everywhere in Canada' | E3: Online (national); based in Quebec | F3: 10%OFF on $500+ (expiry date not readable) | G3: [V]
A4: Kal Tire | B4: Per tire | C4: Not published on pages read | D4: n/a (in-store) | E4: Default site pricing, likely BC (Canada/Pacific cookie) — other provinces not checked | F4: Instant sales on Nokian and Nitto shown | G4: [V] prices · [U] location
A5: Point S | B5: Per tire, 'set of 4 tires installation and environmental costs included' | C5: Included | D5: n/a (in-store) | E5: 'Generic QC Point-S' pricing; participating dealers may differ | F5: Mail-in rebates only | G5: [V]
A6: Costco | B6: Per tire; set-of-4 total shown | C6: Included at no charge (TPMS service pack fees may apply) | D6: n/a (in-store) | E6: Thorncliffe Park, Toronto (#1316) | F6: Bridgestone $100 / Firestone $60 off set of 4, Aug 31–Oct 4; many items 'Sign in for price' | G6: [V]

Sheet Run-flat (excluded)
A1: Size | B1: Brand | C1: Model | D1: Load / speed | E1: Retailer | F1: CAD $/tire | G1: Verif | H1: Why excluded
A2: 225/50R18 | B2: Pirelli | C2: Cinturato P7 All Season Run-Flat | D2: 95V | E2: Costco | F2: 344.99 | G2: [V] | H2: Run-flat; Taos is not fitted with run-flats — listed only because retailers returned it for this size
A3: 225/45R19 | B3: Pirelli | C3: Cinturato P7 All Season Run-Flat | D3: 96H | E3: Costco | F3: 479.99 | G3: [V] | H3: Run-flat; Taos is not fitted with run-flats — listed only because retailers returned it for this size
A4: 225/45R19 | B4: Pirelli | C4: Cinturato P7 A/S Run-Flat | D4: 96H | E4: Kal Tire | F4: 488.67 | G4: [V] | H4: Run-flat; Taos is not fitted with run-flats — listed only because retailers returned it for this size

Sheet Sources
A1: Section | B1: Item | C1: Detail | D1: Status
A2: Sources & verification | B2: OE sizes | C2: 225/50R18 95H and 225/45R19 92H for 2022 Taos Highline 4MOTION — michelin.ca/en/auto/manufacturers/volkswagen/taos/2022/highline-4motion and bfgoodrich.ca/en/auto/manufacturers/volkswagen/taos/2022/highline-4motion | D2: [V] (same parent company — treat as one fitment database)
A3: Sources & verification | B3: OE sizes | C3: VW US 2022 Taos tech specs PDF: 225/50 R18 [AWD], 225/45 R19 all-season — media.vw.com/assets/documents/original/13552-2022TaosTechnicalSpecsFinal.pdf | D3: [V] sizes · no load/speed given
A4: Sources & verification | B4: Highline = 4MOTION only in Canada; 18" std, 19" $500 option | C4: guideautoweb.com/en/makes/volkswagen/taos/2022/specifications/highline-4motion/ ; canadadrives.ca/blog/car-guide/2022-volkswagen-taos-highline-review ; wildsau.ca/2021/12/review-2022-vw-taos/ | D4: [T] — no vw.ca spec page reachable
A5: Sources & verification | B5: Blackcircles.ca prices | C5: blackcircles.ca/en/tire/<brand>/<model>/<size> product data; terms from /en/offers, /en/mail-in-rebate, shipping FAQ | D5: [V]
A6: Sources & verification | B6: PMCtire.com prices | C6: pmctire.com/en/tires/<id> product data feed, spot-checked against product page; terms from /en/promo-codes, /en/mail-in-rebate, /en/about | D6: [V]
A7: Sources & verification | B7: Kal Tire prices | C7: kaltire.com/en/tires/<model>/<id>.html product pages (JSON-LD + page text) | D7: [V] price · [U] province
A8: Sources & verification | B8: Point S prices | C8: point-s.ca/en/tires/225/50/18 and /225/45/19 listings + product pages | D8: [V]
A9: Sources & verification | B9: Costco prices | C9: tires.costco.ca size search + product pages, Thorncliffe Park Tire Centre | D9: [V] where shown; 'Member price' = hidden behind sign-in
A10: Sources & verification | B10: Canadian Tire | C10: canadiantire.ca pages and price API returned 403 (Akamai); WebFetch rendered no prices (JS-only) | D10: NOT CHECKED — no prices
A11: Sources & verification | B11: Walmart.ca | C11: Bot block (307 → /blocked, 'press and hold' challenge). Search snippets showed prices but pages could not be opened; snippet figures not used | D11: NOT CHECKED — no prices
A12: Sources & verification | B12: OK Tire | C12: oktire.com: Cloudflare 403 on every page | D12: NOT CHECKED — no prices
... A20: Conflicts | B20: PMCtire Toyo rebate | C20: Claim deadline shown as 'July 30, 2026' for a Sep–Dec promotion — likely site typo. | D20: Unresolved — confirm before relying on it
A21: NEEDS YOU | B21: 1 | C21: Read the door-jamb placard: 225/50R18 or 225/45R19? Use that size's sheet only.
A22: NEEDS YOU | B22: 2 | C22: Pick all-season (needs separate winters) or all-weather 3PMSF (year-round) — the request left both open.
A23: NEEDS YOU | B23: 3 | C23: Get Canadian Tire / Walmart / OK Tire / Tirecraft quotes manually for your postal code — all blocked automated reads.
A24: NEEDS YOU | B24: 4 | C24: Add installation cost for Blackcircles / PMCtire / Kal Tire quotes before comparing to Costco and Point S (install included).
A25: NEEDS YOU | B25: 5 | C25: Sign in to Costco to see member-only prices (CrossClimate 2, UltraWeather, Defender2, Pilot Sport AS4).
